setup.cfg
setup.py
pycurrency/__init__.py
pycurrency/converter.py
pycurrency.egg-info/PKG-INFO
pycurrency.egg-info/SOURCES.txt
pycurrency.egg-info/dependency_links.txt
pycurrency.egg-info/entry_points.txt
pycurrency.egg-info/not-zip-safe
pycurrency.egg-info/top_level.txt